{
  "version": 1,
  "collection": "items",
  "entries": [
    {
      "id": "cdb0b5d2-8287-4f14-acdb-c5881df01916",
      "collection": "items",
      "name": "Rho's Heart",
      "tags": [],
      "source": "custom",
      "provider": "",
      "providerId": "",
      "variantOf": "",
      "addons": {
        "mechanics": [],
        "equipment": {
          "slot": "",
          "rarity": ""
        }
      },
      "createdAt": "2026-05-03T04:22:03.660Z",
      "updatedAt": "2026-05-03T04:22:03.660Z",
      "type": "wondrous",
      "weight": 67,
      "attuned": true,
      "description": "gives hp or something idk"
    },
    {
      "id": "c20951b4-5a2a-4566-bb0d-dd60f986b037",
      "collection": "items",
      "name": "New item",
      "tags": [],
      "source": "custom",
      "provider": "",
      "providerId": "",
      "variantOf": "",
      "addons": {
        "mechanics": [],
        "equipment": {
          "slot": "",
          "rarity": ""
        }
      },
      "createdAt": "2026-05-03T07:13:51.264Z",
      "updatedAt": "2026-05-03T07:13:51.264Z",
      "type": "misc",
      "weight": null,
      "attuned": false,
      "description": ""
    }
  ]
}